llama_index/readers/myscale/__init__.py
llama_index/readers/myscale/base.py
flying_delta_readers_myscale-0.1.1.dist-info/METADATA
flying_delta_readers_myscale-0.1.1.dist-info/WHEEL
flying_delta_readers_myscale-0.1.1.dist-info/RECORD
